{"State.fcf79014-3a42-42bd-a748-52c0f81b3f40": {"created_at": "2023-09-20T10:58:22.767220", "updated_at": "2023-09-20T10:58:22.868697", "name": "California", "id": "fcf79014-3a42-42bd-a748-52c0f81b3f40", "__class__": "State"}, "State.5d32fb17-c54b-4293-a78d-740a239bc825": {"created_at": "2023-09-20T10:58:22.871125", "updated_at": "2023-09-20T10:58:22.871588", "name": "Arizona", "id": "5d32fb17-c54b-4293-a78d-740a239bc825", "__class__": "State"}, "Place.4dbd1bfe-50bc-44a3-8472-1da3cd02233e": {"created_at": "2023-09-20T10:58:22.874175", "updated_at": "2023-09-20T10:58:22.874670", "city id": 1, "user id": 1, "name": "My_little_house", "number rooms": 4, "number bathrooms": 2, "max guest": 10, "price by night": 300, "latitude": 37.773972, "longitude": -122.431297, "id": "4dbd1bfe-50bc-44a3-8472-1da3cd02233e", "__class__": "Place"}}